[{"disc_number":1,"name":"In Your Honor","duration_ms":1,"track_number":1,"docType":"TRACK"},{"disc_number":1,"name":"No Way Back","duration_ms":1,"track_number":2,"docType":"TRACK"},{"disc_number":1,"name":"Best of You","duration_ms":1,"track_number":3,"docType":"TRACK"},{"disc_number":1,"name":"DOA","duration_ms":1,"track_number":4,"docType":"TRACK"},{"disc_number":1,"name":"Hell","duration_ms":1,"track_number":5,"docType":"TRACK"},{"disc_number":1,"name":"The Last Song","duration_ms":1,"track_number":6,"docType":"TRACK"},{"disc_number":1,"name":"Free Me","duration_ms":1,"track_number":7,"docType":"TRACK"},{"disc_number":1,"name":"Resolve","duration_ms":1,"track_number":8,"docType":"TRACK"},{"disc_number":1,"name":"The Deepest Blues Are Black","duration_ms":1,"track_number":9,"docType":"TRACK"},{"disc_number":1,"name":"End Over End","duration_ms":1,"track_number":10,"docType":"TRACK"},{"disc_number":2,"name":"Still","duration_ms":2,"track_number":1,"docType":"TRACK"},{"disc_number":2,"name":"What If I Do?","duration_ms":2,"track_number":2,"docType":"TRACK"},{"disc_number":2,"name":"Miracle","duration_ms":2,"track_number":3,"docType":"TRACK"},{"disc_number":2,"name":"Another Round","duration_ms":2,"track_number":4,"docType":"TRACK"},{"disc_number":2,"name":"Friend Of A Friend","duration_ms":2,"track_number":5,"docType":"TRACK"},{"disc_number":2,"name":"Over And Out","duration_ms":2,"track_number":6,"docType":"TRACK"},{"disc_number":2,"name":"On The Mend","duration_ms":2,"track_number":7,"docType":"TRACK"},{"disc_number":2,"name":"Virginia Moon","duration_ms":2,"track_number":8,"docType":"TRACK"},{"disc_number":2,"name":"Cold Day In The Sun","duration_ms":2,"track_number":9,"docType":"TRACK"},{"disc_number":2,"name":"Razor","duration_ms":2,"track_number":10,"docType":"TRACK"}]