[{"disc_number":1,"name":"Go (Remastered)","duration_ms":1,"track_number":1,"docType":"TRACK"},{"disc_number":1,"name":"Animal (Remastered)","duration_ms":1,"track_number":2,"docType":"TRACK"},{"disc_number":1,"name":"Daughter (Remastered)","duration_ms":1,"track_number":3,"docType":"TRACK"},{"disc_number":1,"name":"Glorified G (Remastered)","duration_ms":1,"track_number":4,"docType":"TRACK"},{"disc_number":1,"name":"Dissident (Remastered)","duration_ms":1,"track_number":5,"docType":"TRACK"},{"disc_number":1,"name":"W.M.A. (Remastered)","duration_ms":1,"track_number":6,"docType":"TRACK"},{"disc_number":1,"name":"Blood (Remastered)","duration_ms":1,"track_number":7,"docType":"TRACK"},{"disc_number":1,"name":"Rearviewmirror (Remastered)","duration_ms":1,"track_number":8,"docType":"TRACK"},{"disc_number":1,"name":"Rats (Remastered)","duration_ms":1,"track_number":9,"docType":"TRACK"},{"disc_number":1,"name":"Elderly Woman Behind the Counter in a Small Town (Remastered)","duration_ms":1,"track_number":10,"docType":"TRACK"},{"disc_number":1,"name":"Leash (Remastered)","duration_ms":1,"track_number":11,"docType":"TRACK"},{"disc_number":1,"name":"Indifference (Remastered)","duration_ms":1,"track_number":12,"docType":"TRACK"},{"disc_number":1,"name":"Hold On - bonus track","duration_ms":1,"track_number":13,"docType":"TRACK"},{"disc_number":1,"name":"Cready Stomp - bonus track","duration_ms":1,"track_number":14,"docType":"TRACK"},{"disc_number":1,"name":"Crazy Mary (Remastered)","duration_ms":1,"track_number":15,"docType":"TRACK"}]