[{"disc_number":1,"name":"The Getaway","duration_ms":1,"track_number":1,"docType":"TRACK"},{"disc_number":1,"name":"Dark Necessities","duration_ms":1,"track_number":2,"docType":"TRACK"},{"disc_number":1,"name":"We Turn Red","duration_ms":1,"track_number":3,"docType":"TRACK"},{"disc_number":1,"name":"The Longest Wave","duration_ms":1,"track_number":4,"docType":"TRACK"},{"disc_number":1,"name":"Goodbye Angels","duration_ms":1,"track_number":5,"docType":"TRACK"},{"disc_number":1,"name":"Sick Love","duration_ms":1,"track_number":6,"docType":"TRACK"},{"disc_number":1,"name":"Go Robot","duration_ms":1,"track_number":7,"docType":"TRACK"},{"disc_number":1,"name":"Feasting on the Flowers","duration_ms":1,"track_number":8,"docType":"TRACK"},{"disc_number":1,"name":"Detroit","duration_ms":1,"track_number":9,"docType":"TRACK"},{"disc_number":1,"name":"This Ticonderoga","duration_ms":1,"track_number":10,"docType":"TRACK"},{"disc_number":1,"name":"Encore","duration_ms":1,"track_number":11,"docType":"TRACK"},{"disc_number":1,"name":"The Hunter","duration_ms":1,"track_number":12,"docType":"TRACK"},{"disc_number":1,"name":"Dreams of a Samurai","duration_ms":1,"track_number":13,"docType":"TRACK"}]