{
  "id": "e2615197-7744-b6e7-ff46-90d488cb66e7",
  "name": "local",
  "values": [
    {
      "key": "server",
      "value": "localhost:5000",
      "type": "text",
      "enabled": true
    },
    {
      "key": "bandId",
      "value": "I0ETl8oDZJ9fXxp3",
      "type": "text",
      "enabled": true
    },
    {
      "key": "albumId",
      "value": "0f9qO0HL9nJkmzu4",
      "type": "text",
      "enabled": true
    },
    {
      "key": "artistId",
      "value": "3UL9Vk62NZOdP3m4",
      "type": "text",
      "enabled": true
    },
    {
      "key": "trackId",
      "value": "01m3gq2ejrrY6n3f",
      "type": "text",
      "enabled": true
    }
  ],
  "timestamp": 1479266652950,
  "_postman_variable_scope": "environment",
  "_postman_exported_at": "2016-11-16T03:24:14.626Z",
  "_postman_exported_using": "Postman/4.8.3"
}